{"format":2,"version":"6.5.0","globals":"2ed476c54f1e3c7557311e99e3b1b080","files":{"d_0203103e395d7d41___init___py":{"hash":"c85c5930e79b996387ad58ff0fa5948e","index":{"nums":[2,1,6,0,0,0,0,0],"html_filename":"d_0203103e395d7d41___init___py.html","relative_filename":"teiphy/__init__.py"}},"d_0203103e395d7d41_collation_py":{"hash":"bda47960a1c086dc71c91242a617c490","index":{"nums":[2,1,1262,0,1,0,0,0],"html_filename":"d_0203103e395d7d41_collation_py.html","relative_filename":"teiphy/collation.py"}},"d_0203103e395d7d41_common_py":{"hash":"dd192d265aa6781e5c3b4ebe5b7dd1fd","index":{"nums":[2,1,3,0,0,0,0,0],"html_filename":"d_0203103e395d7d41_common_py.html","relative_filename":"teiphy/common.py"}},"d_0203103e395d7d41_format_py":{"hash":"10485db11e788c52329d4162e4bb0d8e","index":{"nums":[2,1,21,0,0,0,0,0],"html_filename":"d_0203103e395d7d41_format_py.html","relative_filename":"teiphy/format.py"}},"d_0203103e395d7d41_main_py":{"hash":"09e39295da1287cbff831c1db68d4dd3","index":{"nums":[2,1,33,0,0,0,0,0],"html_filename":"d_0203103e395d7d41_main_py.html","relative_filename":"teiphy/main.py"}},"d_0203103e395d7d41_reading_py":{"hash":"e94fb9220f3d6356a7ff594ef52b34b4","index":{"nums":[2,1,162,0,0,0,0,0],"html_filename":"d_0203103e395d7d41_reading_py.html","relative_filename":"teiphy/reading.py"}},"d_0203103e395d7d41_variation_unit_py":{"hash":"598963371a94d854a7555fdfebc061fb","index":{"nums":[2,1,114,0,0,0,0,0],"html_filename":"d_0203103e395d7d41_variation_unit_py.html","relative_filename":"teiphy/variation_unit.py"}},"d_0203103e395d7d41_witness_py":{"hash":"b47c9828a0db563f8bd43a01de49a30e","index":{"nums":[2,1,30,0,0,0,0,0],"html_filename":"d_0203103e395d7d41_witness_py.html","relative_filename":"teiphy/witness.py"}}}}